sedna/__init__.py
sedna/convert.py
sedna/maths.py
sedna/physics.py
sedna/prime.py
sedna/system.py
sedna/voice.py
Sedna-0.1.2.dist-info/LICENSE
Sedna-0.1.2.dist-info/METADATA
Sedna-0.1.2.dist-info/WHEEL
Sedna-0.1.2.dist-info/top_level.txt
Sedna-0.1.2.dist-info/RECORD
