Metadata-Version: 2.1
Name: Sedna
Version: 0.1.2
Summary: Sedna is a python package for computational mathematics
Author-email: Rishit Logar <logarrishit@gmail.com>
Project-URL: Homepage, https://github.com/logarrishit/Sedna/
Project-URL: Issues, https://github.com/logarrishit/Sedna/issues
Classifier: Programming Language :: Python :: 3
Classifier: License :: OSI Approved :: MIT License
Classifier: Operating System :: OS Independent
Classifier: Intended Audience :: Developers
Requires-Python: >=3.8
License-File: LICENSE
